ipath/__init__.py
ipath/draw.py
ipath/main.py
ipath/reader.py
ipath-0.0.2.dist-info/LICENSE
ipath-0.0.2.dist-info/METADATA
ipath-0.0.2.dist-info/WHEEL
ipath-0.0.2.dist-info/entry_points.txt
ipath-0.0.2.dist-info/top_level.txt
ipath-0.0.2.dist-info/RECORD
