Metadata-Version: 2.1
Name: ipath
Version: 0.0.2
Summary: Apollo path and simple map making tool.
Home-page: https://github.com/daohu527/ipath
Author: daohu527
Author-email: daohu527@gmail.com
License: UNKNOWN
Project-URL: Bug Tracker, https://github.com/daohu527/ipath/issues
Platform: UNKNOWN
Classifier: Programming Language :: Python :: 3
Classifier: License :: OSI Approved :: Apache Software License
Classifier: Operating System :: OS Independent
Requires-Python: >=3.6
Requires-Dist: protobuf
Requires-Dist: matplotlib
Requires-Dist: record-msg
